sudarshan/__init__.py
sudarshan/_bindings.py
sudarshan/crypto.py
sudarshan_engine-1.0.0b7.dist-info/METADATA
sudarshan_engine-1.0.0b7.dist-info/WHEEL
sudarshan_engine-1.0.0b7.dist-info/top_level.txt
sudarshan_engine-1.0.0b7.dist-info/RECORD
