Metadata-Version: 2.4
Name: sudarshan-engine
Version: 1.0.0b7
Summary: Python bindings for Sudarshan Engine - A high-performance cryptographic library providing post-quantum secure algorithms including KEM, signatures, symmetric encryption, and hashing.
Author: Sudarshan Team
License: MIT
Classifier: Programming Language :: Python :: 3
Classifier: License :: OSI Approved :: MIT License
Classifier: Operating System :: OS Independent
